cafedb/cafedb.py
cafedb/init.py
cafedb/main.py
cafedb/usage.py
cafedb-0.0.2.dist-info/licenses/LICENSE.txt
cafedb-0.0.2.dist-info/METADATA
cafedb-0.0.2.dist-info/WHEEL
cafedb-0.0.2.dist-info/entry_points.txt
cafedb-0.0.2.dist-info/top_level.txt
cafedb-0.0.2.dist-info/RECORD
