Metadata-Version: 2.4
Name: cafedb
Version: 0.0.2
Summary: CafeDB: A Python-native, lightweight, schema-flexible, JSONL database with set-indexed querying, Python-native type support, and safe append-only storage.
Author-email: Sivaprasad Murali <sivaprasad.off@gmail.com>
License: MIT
Project-URL: Homepage, https://github.com/Crystallinecore/cafedb
Project-URL: Documentation, https://github.com/Crystallinecore/cafedb#readme
Project-URL: Source, https://github.com/Crystallinecore/cafedb
Project-URL: Tracker, https://github.com/Crystallinecore/cafedb/issues
Project-URL: Releases, https://github.com/Crystallinecore/cafedb/releases
Keywords: database,jsonl,python,dbms,cli,schema-less,indexing,hash,set-indexed,append-only,lightweight,portable,python-native,query,insert,update,delete,conflict-resolution,storage,data-integrity
Classifier: Development Status :: 4 - Beta
Classifier: Environment :: Console
Classifier: Intended Audience :: Developers
Classifier: Intended Audience :: Education
Classifier: License :: OSI Approved :: MIT License
Classifier: Operating System :: OS Independent
Classifier: Programming Language :: Python
Classifier: Programming Language :: Python :: 3
Classifier: Programming Language :: Python :: 3.8
Classifier: Programming Language :: Python :: 3.9
Classifier: Programming Language :: Python :: 3.10
Classifier: Programming Language :: Python :: 3.11
Classifier: Programming Language :: Python :: 3.12
Classifier: Topic :: Database
Classifier: Topic :: Software Development :: Libraries :: Python Modules
Requires-Python: >=3.8
License-File: LICENSE.txt
Requires-Dist: jsonlines>=2.0.0
Dynamic: license-file
